helpers/__init__.py
helpers/common_imports.py
helpers/utilities.py
helpers_drscook-1.1.0.dist-info/LICENSE
helpers_drscook-1.1.0.dist-info/METADATA
helpers_drscook-1.1.0.dist-info/WHEEL
helpers_drscook-1.1.0.dist-info/top_level.txt
helpers_drscook-1.1.0.dist-info/RECORD
