Metadata-Version: 2.1
Name: helpers-drscook
Version: 1.1.0
Summary: helpers
Home-page: https://github.com/drscookconfig
Author: Scott Cook
Author-email: scook@tarleton.edu
Keywords: pypi,python
Classifier: Programming Language :: Python :: 3
License-File: LICENSE
Requires-Dist: codetiming
Requires-Dist: shutils
Requires-Dist: numpy
Requires-Dist: pandas
Requires-Dist: matplotlib
